benchmark_runner/__init__.py
benchmark_runner/benchmark_operator/__init__.py
benchmark_runner/benchmark_operator/benchmark_operator_exceptions.py
benchmark_runner/benchmark_operator/benchmark_operator_workloads.py
benchmark_runner/benchmark_operator/benchmark_operator_workloads_operations.py
benchmark_runner/benchmark_operator/hammerdb_pod.py
benchmark_runner/benchmark_operator/hammerdb_vm.py
benchmark_runner/benchmark_operator/stressng_pod.py
benchmark_runner/benchmark_operator/stressng_vm.py
benchmark_runner/benchmark_operator/uperf_pod.py
benchmark_runner/benchmark_operator/uperf_vm.py
benchmark_runner/clusterbuster/__init__.py
benchmark_runner/clusterbuster/clusterbuster_exceptions.py
benchmark_runner/clusterbuster/clusterbuster_workloads.py
benchmark_runner/common/__init__.py
benchmark_runner/common/analyze/__init__.py
benchmark_runner/common/analyze/analyze_data.py
benchmark_runner/common/assisted_installer/__init__.py
benchmark_runner/common/assisted_installer/assisted_installer_latest_version.py
benchmark_runner/common/assisted_installer/jetlag/run_jetlag.sh
benchmark_runner/common/clouds/__init__.py
benchmark_runner/common/clouds/Azure/__init__.py
benchmark_runner/common/clouds/Azure/azure_operations.py
benchmark_runner/common/clouds/BareMetal/__init__.py
benchmark_runner/common/clouds/BareMetal/bare_metal_exceptions.py
benchmark_runner/common/clouds/BareMetal/bare_metal_operations.py
benchmark_runner/common/clouds/IBM/__init__.py
benchmark_runner/common/clouds/IBM/ibm_exceptions.py
benchmark_runner/common/clouds/IBM/ibm_operations.py
benchmark_runner/common/clouds/shared/__init__.py
benchmark_runner/common/clouds/shared/s3/__init__.py
benchmark_runner/common/clouds/shared/s3/s3_operations.py
benchmark_runner/common/clouds/shared/s3/s3_operations_exceptions.py
benchmark_runner/common/elasticsearch/__init__.py
benchmark_runner/common/elasticsearch/elasticsearch_exceptions.py
benchmark_runner/common/elasticsearch/elasticsearch_operations.py
benchmark_runner-1.0.937.dist-info/licenses/LICENSE
benchmark_runner-1.0.937.dist-info/METADATA
benchmark_runner-1.0.937.dist-info/WHEEL
benchmark_runner-1.0.937.dist-info/top_level.txt
benchmark_runner-1.0.937.dist-info/RECORD
