Metadata-Version: 2.4
Name: benchmark-runner
Version: 1.0.937
Summary: Benchmark Runner Tool
Home-page: https://github.com/redhat-performance/benchmark-runner
Author: Red Hat
Author-email: ebattat@redhat.com
License: Apache License 2.0
Classifier: License :: OSI Approved :: Apache Software License
Classifier: Programming Language :: Python :: 3
Classifier: Programming Language :: Python :: 3.10
Classifier: Programming Language :: Python :: 3.11
Classifier: Programming Language :: Python :: 3.12
Classifier: Programming Language :: Python :: 3.13
Classifier: Programming Language :: Python :: 3.14
License-File: LICENSE
Requires-Dist: attrs==21.4.0
Requires-Dist: azure==4.0.0
Requires-Dist: boto3==1.33.13
Requires-Dist: botocore==1.33.13
Requires-Dist: cryptography==44.0.1
Requires-Dist: elasticsearch==7.16.1
Requires-Dist: elasticsearch-dsl==7.4.0
Requires-Dist: google-auth==2.30.0
Requires-Dist: google-auth-httplib2==0.2.0
Requires-Dist: google-auth-oauthlib==1.2.0
Requires-Dist: google-api-python-client==2.135.0
Requires-Dist: ipywidgets==8.0.6
Requires-Dist: jinja2==3.1.6
Requires-Dist: myst-parser==1.0.0
Requires-Dist: openshift-client==1.0.17
Requires-Dist: prometheus-api-client==0.5.1
Requires-Dist: pandas
Requires-Dist: paramiko==3.4.0
Requires-Dist: PyGitHub==1.55
Requires-Dist: PyYAML==6.0.1
Requires-Dist: setuptools
Requires-Dist: sphinx==5.0.0
Requires-Dist: sphinx-rtd-theme==1.0.0
Requires-Dist: tenacity==8.0.1
Requires-Dist: tqdm==4.66.3
Requires-Dist: typeguard==2.12.1
Requires-Dist: typing==3.7.4.3
Dynamic: author
Dynamic: author-email
Dynamic: classifier
Dynamic: description
Dynamic: description-content-type
Dynamic: home-page
Dynamic: license
Dynamic: license-file
Dynamic: requires-dist
Dynamic: summary
